Metadata-Version: 1.1
Name: tlp
Version: 0.1.1
Summary: tlp is a python library that parses a body of text for indicators of compromise (iocs) using natural language processing modules to derive their context.
Home-page: http://github.com/ministryofpromise/tlp
Author: { ministry of promise }
Author-email: adam.j.nichols@gmail.com
License: MIT
Keywords: tlp threat language parser ioc nlp textblob nltk
Platform: UNKNOWN
Classifier: Development Status :: 3 - Alpha
Classifier: Topic :: Utilities
Classifier: License :: OSI Approved :: MIT License
